sigparse/__init__.py
sigparse/_applicator.py
sigparse/_classparse.py
sigparse/_pep604.py
sigparse/_sigparse.py
sigparse/py.typed
sigparse/utils.py
sigparse-3.0.0.dist-info/METADATA
sigparse-3.0.0.dist-info/WHEEL
sigparse-3.0.0.dist-info/LICENSE
sigparse-3.0.0.dist-info/RECORD
