Metadata-Version: 2.1
Name: sigparse
Version: 3.0.0
Summary: Backports python3.10 typing features into python 3.7 and newer.
Home-page: https://github.com/Lunarmagpie/sigparse
License: MIT
Author: Lunarmagpie
Author-email: bambolambo0@gmail.com
Requires-Python: >=3.7
Classifier: License :: OSI Approved :: MIT License
Classifier: Programming Language :: Python :: 3
Classifier: Programming Language :: Python :: 3.7
Classifier: Programming Language :: Python :: 3.8
Classifier: Programming Language :: Python :: 3.9
Classifier: Programming Language :: Python :: 3.10
Classifier: Programming Language :: Python :: 3.11
Requires-Dist: forbiddenfruit (>=0.1.4,<0.2.0) ; python_version < "3.10"
Project-URL: Bug Tracker, https://github.com/python-poetry/poetry/issues
